cognite/pygen/__init__.py
cognite/pygen/_build.py
cognite/pygen/_constants.py
cognite/pygen/_generator.py
cognite/pygen/_settings.py
cognite/pygen/_version.py
cognite/pygen/_warnings.py
cognite/pygen/cli.py
cognite/pygen/exceptions.py
cognite/pygen/_core/__init__.py
cognite/pygen/_core/generators.py
cognite/pygen/_core/validation.py
cognite/pygen/_core/models/__init__.py
cognite/pygen/_core/models/api_classes.py
cognite/pygen/_core/models/data_classes.py
cognite/pygen/_core/models/filter_methods.py
cognite/pygen/_core/models/fields/__init__.py
cognite/pygen/_core/models/fields/base.py
cognite/pygen/_core/models/fields/cdf_reference.py
cognite/pygen/_core/models/fields/connections.py
cognite/pygen/_core/models/fields/primitive.py
cognite/pygen/_core/templates/__init__.py
cognite/pygen/_core/templates/_api_client_multi_model.py.jinja
cognite/pygen/_core/templates/_api_client_single_model.py.jinja
cognite/pygen/_core/templates/_client_init.py.jinja
cognite/pygen/_core/templates/api_class_edge.py.jinja
cognite/pygen/_core/templates/api_class_node.py.jinja
cognite/pygen/_core/templates/api_class_query.py.jinja
cognite/pygen/_core/templates/api_core.py.jinja
cognite/pygen/_core/templates/api_init.py.jinja
cognite/pygen/_core/templates/config.py.jinja
cognite/pygen/_core/templates/data_class_edge.py.jinja
cognite/pygen/_core/templates/data_class_node.py.jinja
cognite/pygen/_core/templates/data_classes_core_base.py.jinja
cognite/pygen/_core/templates/data_classes_core_cdf_external.py.jinja
cognite/pygen/_core/templates/data_classes_core_constants.py.jinja
cognite/pygen/_core/templates/data_classes_core_datapoints_api.py.jinja
cognite/pygen/_core/templates/data_classes_core_filecontent_api.py.jinja
cognite/pygen/_core/templates/data_classes_core_helpers.py.jinja
cognite/pygen/_core/templates/data_classes_core_init.py.jinja
cognite/pygen/_core/templates/data_classes_core_query_filter_classes.py.jinja
cognite/pygen/_core/templates/data_classes_core_query_init.py.jinja
cognite_pygen-1.2.29.dist-info/METADATA
cognite_pygen-1.2.29.dist-info/WHEEL
cognite_pygen-1.2.29.dist-info/entry_points.txt
cognite_pygen-1.2.29.dist-info/licenses/LICENSE
cognite_pygen-1.2.29.dist-info/RECORD
