Metadata-Version: 2.4
Name: cognite-pygen
Version: 1.2.29
Summary: Cognite Python SDK Generator
Project-URL: Documentation, https://cognite-pygen.readthedocs-hosted.com/en/latest/
Project-URL: Homepage, https://cognite-pygen.readthedocs-hosted.com/en/latest/
Project-URL: Repository, https://github.com/cognitedata/pygen
Project-URL: Changelog, https://github.com/cognitedata/pygen/releases
Author-email: Cognite <support@cognite.com>
License-Expression: Apache-2.0
License-File: LICENSE
Requires-Python: <4.0,>=3.10
Requires-Dist: cognite-sdk<8.0.0,>=7.86.0
Requires-Dist: inflect>=6.2
Requires-Dist: jinja2>=3.1
Requires-Dist: pydantic>=2.7
Requires-Dist: typing-extensions>=4.14.0
Provides-Extra: cli
Requires-Dist: build>=1.1; extra == 'cli'
Requires-Dist: packaging>=21.3; extra == 'cli'
Requires-Dist: toml>=0.10; extra == 'cli'
Requires-Dist: typer>=0.9; extra == 'cli'
Provides-Extra: format
Requires-Dist: black>=24.4.2; extra == 'format'
